aa_contacts/__init__.py
aa_contacts/admin.py
aa_contacts/app_settings.py
aa_contacts/apps.py
aa_contacts/auth_hooks.py
aa_contacts/charlink_hook.py
aa_contacts/forms.py
aa_contacts/models.py
aa_contacts/providers.py
aa_contacts/tasks.py
aa_contacts/urls.py
aa_contacts/views.py
aa_contacts/api/__init__.py
aa_contacts/api/permissions.py
aa_contacts/api/schema.py
aa_contacts/api/alliance/__init__.py
aa_contacts/api/alliance/contacts.py
aa_contacts/api/alliance/tokens.py
aa_contacts/api/corporation/__init__.py
aa_contacts/api/corporation/contacts.py
aa_contacts/api/corporation/tokens.py
aa_contacts/locale/de/LC_MESSAGES/django.mo
aa_contacts/locale/de/LC_MESSAGES/django.po
aa_contacts/locale/en/LC_MESSAGES/django.mo
aa_contacts/locale/en/LC_MESSAGES/django.po
aa_contacts/locale/it_IT/LC_MESSAGES/django.mo
aa_contacts/locale/it_IT/LC_MESSAGES/django.po
aa_contacts/migrations/0001_initial.py
aa_contacts/migrations/0002_alter_general_options_alter_alliancecontact_labels_and_more.py
aa_contacts/migrations/0003_corporationcontact_is_watched_corporationtoken.py
aa_contacts/migrations/0004_standingfilter.py
aa_contacts/migrations/0005_standingfilter_check_type_standingfilter_only_main.py
aa_contacts/migrations/__init__.py
aa_contacts/static/aa_contacts/react/manifest.json
aa_contacts/static/aa_contacts/react/assets/@bootstrap-libs-BKvb8Mv0.js
aa_contacts/static/aa_contacts/react/assets/@bootstrap-libs-BKvb8Mv0.js.map
aa_contacts/static/aa_contacts/react/assets/@datatables-libs-BKeJhCsl.js
aa_contacts/static/aa_contacts/react/assets/@datatables-libs-BKeJhCsl.js.map
aa_contacts/static/aa_contacts/react/assets/@lang-libs-DVJcKnxu.js
aa_contacts/static/aa_contacts/react/assets/@lang-libs-DVJcKnxu.js.map
aa_contacts/static/aa_contacts/react/assets/@react-libs-Da1HkQmp.js
aa_contacts/static/aa_contacts/react/assets/@react-libs-Da1HkQmp.js.map
aa_contacts/static/aa_contacts/react/assets/browser-ponyfill-CuqxTsru.js
aa_contacts-0.10.2.dist-info/licenses/LICENSE
aa_contacts-0.10.2.dist-info/WHEEL
aa_contacts-0.10.2.dist-info/METADATA
aa_contacts-0.10.2.dist-info/RECORD
