Metadata-Version: 2.4
Name: aa-contacts
Version: 0.10.2
Summary: Contacts tool for AllianceAuth
Keywords: allianceauth,eveonline,allianceauth_contacts,contacts,aa-contacts
Author-email: Matteo Ghia <matteo.ghia@yahoo.it>
Requires-Python: ~=3.10
Classifier: Environment :: Web Environment
Classifier: Framework :: Django
Classifier: Framework :: Django :: 4
Classifier: Framework :: Django :: 4.2
Classifier: Operating System :: POSIX :: Linux
Classifier: Development Status :: 3 - Alpha
Classifier: Intended Audience :: Developers
Classifier: License :: OSI Approved :: GNU General Public License v3 (GPLv3)
Classifier: Natural Language :: English
Classifier: Programming Language :: Python :: 3
Classifier: Programming Language :: Python :: 3.10
Classifier: Programming Language :: Python :: 3.11
Classifier: Programming Language :: Python :: 3.12
Classifier: Programming Language :: Python :: 3.13
Classifier: Topic :: Internet :: WWW/HTTP
Classifier: Topic :: Internet :: WWW/HTTP :: Dynamic Content
License-File: LICENSE
Requires-Dist: allianceauth~=4.6
Requires-Dist: allianceauth-app-utils>=1.14,<3.0
Requires-Dist: django-esi~=8.0
Requires-Dist: django-ninja~=1.4
Project-URL: Changelog, https://github.com/Maestro-Zacht/aa-contacts/releases
Project-URL: Homepage, https://github.com/Maestro-Zacht/aa-contacts
Project-URL: Source, https://github.com/Maestro-Zacht/aa-contacts
Project-URL: Tracker, https://github.com/Maestro-Zacht/aa-contacts/issues
